sample/__init__.py
sample/result.py
sample/sample.py
sample_kd-0.1.7.data/data/sample.exe
sample_kd-0.1.7.dist-info/DESCRIPTION.rst
sample_kd-0.1.7.dist-info/METADATA
sample_kd-0.1.7.dist-info/RECORD
sample_kd-0.1.7.dist-info/WHEEL
sample_kd-0.1.7.dist-info/metadata.json
sample_kd-0.1.7.dist-info/top_level.txt
