Metadata-Version: 2.0
Name: sample-kd
Version: 0.1.7
Summary: sample data and analysis
Home-page: https://github.com/KD-Group/Half.Sample
Author: Jefung
Author-email: jefung865424525@gmail.com
License: UNKNOWN
Platform: UNKNOWN
Classifier: Programming Language :: Python :: 3
Classifier: License :: OSI Approved :: MIT License
Classifier: Operating System :: OS Independent
